main.py
mcp_mm_cs-0.1.0.dist-info/METADATA
mcp_mm_cs-0.1.0.dist-info/WHEEL
mcp_mm_cs-0.1.0.dist-info/entry_points.txt
mcp_mm_cs-0.1.0.dist-info/top_level.txt
mcp_mm_cs-0.1.0.dist-info/RECORD
